[
  {
    "title": "Watch Our 2017 Steamworks Robot Reveal Video!",
    "date": "July 20, 2017 3:58 P.M.",
    "link": "/media/news",
    "author": "Larry Tseng",
    "media": "<iframe class='card-img-top' src='https://www.youtube.com/embed/YrOXxlsnZ70' frameborder='0' allowfullscreen></iframe>",
    "content": ""
  },
  {
    "title": "Watch Our 2017 Steamworks Robot Reveal Video!",
    "date": "July 20, 2017 3:58 P.M.",
    "link": "",
    "author": "Larry Tseng",
    "media": "<iframe class='card-img-top' src='https://www.youtube.com/embed/YrOXxlsnZ70' frameborder='0' allowfullscreen></iframe>",
    "content": ""
  },
  {
    "title": "Watch Our 2017 Steamworks Robot Reveal Video!",
    "date": "July 20, 2017 3:58 P.M.",
    "link": "",
    "author": "Larry Tseng",
    "media": "<iframe class='card-img-top' src='https://www.youtube.com/embed/YrOXxlsnZ70' frameborder='0' allowfullscreen></iframe>",
    "content": ""
  }
]