[
  {
    "year":"2018",
    "robotName":"",
    "competition":"Power Up",
    "image":"2018firstpowerup_compressed.png",
    "link":"robot-pages/2018powerup.html",
    "description":"This is a robot we made in 2018"
  },
  {
    "year": "2017",
    "robotName": "",
    "competition": "Steamworks",
    "image": "2017steamworks_compressed.png",
    "link": "robot-pages/2017steamworks.html",
    "description":"This is our best robot yet"
  },
  {
    "year": "2016",
    "robotName": "",
    "competition": "Stronghold",
    "image": "2016stronghold_compressed.png",
    "link": "robot-pages/2016stronghold.html",
    "description":"This one was not our best robot"
  },
  {
    "year": "2015",
    "robotName": "",
    "competition": "Recycle Rush",
    "image": "2015recyclerush_compressed.png",
    "link": "robot-pages/2015recyclerush.html",
    "description":"This one was good at lifting boxes"
  },
  {
    "year": "2015",
    "robotName": "T-shirt Cannon",
    "competition": "",
    "image": "2015tshirtcannon_compressed.png",
    "link": "robot-pages/2015tshirtcannon.html",
    "description":"This one shot T-shirts pretty well"
  }
]
